landlab-2.10.1.dist-info/entry_points.txt
landlab-2.10.1.dist-info/WHEEL
landlab-2.10.1.dist-info/METADATA
landlab-2.10.1.dist-info/top_level.txt
landlab-2.10.1.dist-info/RECORD
landlab-2.10.1.dist-info/licenses/AUTHORS.md
landlab-2.10.1.dist-info/licenses/LICENSE.md
landlab/_registry.py
landlab/_version.py
landlab/__init__.py
landlab/_info.py
landlab/graph/graph_convention.py
landlab/graph/dual.py
landlab/graph/graph.py
landlab/graph/__init__.py
landlab/graph/ugrid.py
landlab/graph/voronoi/__init__.py
landlab/graph/voronoi/voronoi.py
landlab/graph/voronoi/dual_voronoi.py
landlab/graph/voronoi/voronoi_to_graph.py
landlab/graph/voronoi/ext/voronoi.cpython-311-aarch64-linux-gnu.so
landlab/graph/voronoi/ext/voronoi.pyx
landlab/graph/voronoi/ext/voronoi.c
landlab/graph/voronoi/ext/__init__.py
landlab/graph/voronoi/ext/delaunay.cpython-311-aarch64-linux-gnu.so
landlab/graph/voronoi/ext/delaunay.c
landlab/graph/voronoi/ext/delaunay.pyx
landlab/graph/object/at_patch.py
landlab/graph/object/at_node.py
landlab/graph/object/__init__.py
landlab/graph/object/ext/at_node.cpython-311-aarch64-linux-gnu.so
landlab/graph/object/ext/at_node.c
landlab/graph/object/ext/at_patch.cpython-311-aarch64-linux-gnu.so
landlab/graph/object/ext/at_node.pyx
landlab/graph/object/ext/__init__.py
landlab/graph/object/ext/at_patch.pyx
landlab/graph/object/ext/at_patch.c
landlab/graph/hex/dual_hex.py
landlab/graph/hex/__init__.py
landlab/graph/hex/hex.py
landlab/graph/hex/ext/perimeternodes.c
landlab/graph/hex/ext/perimeternodes.pyx
landlab/graph/hex/ext/__init__.py
landlab/graph/hex/ext/perimeternodes.cpython-311-aarch64-linux-gnu.so
landlab/graph/hex/ext/hex.c
landlab/graph/hex/ext/hex.cpython-311-aarch64-linux-gnu.so
landlab/graph/hex/ext/hex.pyx
landlab/graph/ext/__init__.py
landlab/graph/quantity/of_patch.py
landlab/graph/quantity/__init__.py
landlab/graph/quantity/of_link.py
landlab/graph/quantity/ext/of_patch.pyx
landlab/graph/quantity/ext/of_element.c
landlab/graph/quantity/ext/of_link.cpython-311-aarch64-linux-gnu.so
landlab/graph/quantity/ext/of_link.c
landlab/graph/quantity/ext/__init__.py
landlab/graph/quantity/ext/of_element.cpython-311-aarch64-linux-gnu.so
