Metadata-Version: 2.4
Name: landlab
Version: 2.10.1
Summary: Open-source Python package for numerical modeling of Earth surface dynamics.
Author: The landlab team
Author-email: mcflugen@gmail.com
Maintainer: The landlab team
Maintainer-email: mcflugen@gmail.com
License: MIT
Project-URL: homepage, https://github.com/landlab
Project-URL: documentation, https://landlab.csdms.io
Project-URL: repository, https://github.com/landlab
Project-URL: changelog, https://github.com/landlab/landlab/blob/develop/CHANGES.md
Keywords: bmi,component modeling,earth science,gridding engine,model coupling,numerical modeling
Classifier: Development Status :: 4 - Beta
Classifier: Intended Audience :: Science/Research
Classifier: License :: OSI Approved :: MIT License
Classifier: Operating System :: OS Independent
Classifier: Programming Language :: Cython
Classifier: Programming Language :: Python :: 3
Classifier: Programming Language :: Python :: 3.11
Classifier: Programming Language :: Python :: 3.12
Classifier: Programming Language :: Python :: 3.13
Classifier: Programming Language :: Python :: Implementation :: CPython
Classifier: Topic :: Scientific/Engineering :: Physics
Requires-Python: >=3.11
License-File: LICENSE.md
License-File: AUTHORS.md
Requires-Dist: bmipy
Requires-Dist: importlib-resources; python_version < "3.12"
Requires-Dist: matplotlib
Requires-Dist: netcdf4
Requires-Dist: numpy>=1.20
Requires-Dist: pyyaml
Requires-Dist: pyshp!=2.3.0
Requires-Dist: rich-click
Requires-Dist: scipy
Requires-Dist: statsmodels
Requires-Dist: pandas
Requires-Dist: xarray>=0.16
Provides-Extra: dev
Requires-Dist: nox; extra == "dev"
Provides-Extra: testing
Requires-Dist: coverage; extra == "testing"
Requires-Dist: hypothesis; extra == "testing"
Requires-Dist: pytest; extra == "testing"
Requires-Dist: pytest-datadir; extra == "testing"
Requires-Dist: pytest-xdist; extra == "testing"
Dynamic: license-file
